Workbook
Name OperatingCostsMonthly: OPERATING_COSTS!$B$14
Name ClinicMargin: MODEL!$B$5
Name NetProfit: MODEL!$B$12
Name InitialCapitalContribution: INPUTS!$B$26
Name Input_Variables: DASHBOARD!$N$38

Sheet INPUTS
A1: VARIABLE [DRAFT_OP_V5] | B1: VALUE [DRAFT_OP_V5] | C1: STATUS [DRAFT_OP_V5]
A2: Clinic % [DRAFT_OP_V5] | B2: 0.33 | C2: [VERIFIED]
A3: Utilization (Path B ref.) [DRAFT_OP_V5] | B3: 0.8 | C3: [PENDING_DATA]
A4: Weeks/year [DRAFT_OP_V5] | B4: 48 | C4: [PENDING_DATA]
A5: Weeks/month factor (sessions equiv.) [DRAFT_OP_V5] | B5: =52/12
A6: Partner_L_Draw — fixed target (CAD/mo) [DRAFT_OP_V5] | B6: 2000 | C6: [VERIFIED]
A7: Director — admin hours/month [DRAFT_OP_V5] | B7: 20 | C7: [PENDING_DATA]
A8: Director_Admin_Rate ($/hr) [DRAFT_OP_V5] | B8: 75 | C8: [VERIFIED]
A9: Director — clinical sessions/month [DRAFT_OP_V5] | B9: 0 | C9: [PENDING_DATA]
A10: Director billing rate — Senior (CAD/session) [DRAFT_OP_V5] | B10: 190 | C10: [VERIFIED]
A11: Director clinical pay — 65% × Senior rate (=0.65×billing) [DRAFT_OP_V5] | B11: =0.65*B10
A12: Min roster count (activate fees) [DRAFT_OP_V5] | B12: 1 | C12: [PENDING_DATA]
A13: Supervision — hours/month [DRAFT_OP_V5] | B13: 0 | C13: [PENDING_DATA]
A14: Supervision — rate (CAD/hr) [DRAFT_OP_V5] | B14: 150 | C14: [VERIFIED]
A15: Admin / platform flat fee (CAD/mo) [DRAFT_OP_V5] | B15: 0 | C15: [PENDING_DATA]
A16: Director legacy — % of roster gross [DRAFT_OP_V5] | B16: 0 | C16: [PENDING_DATA]
A17: Director legacy — $/session (roster volume) [DRAFT_OP_V5] | B17: 0 | C17: [PENDING_DATA]
A19: Tax rate — clinic [DRAFT_OP_V5] | B19: 0.3 | C19: [PENDING_DATA]
A20: Planning — NP benchmark (not an expense) [DRAFT_OP_V5] | B20: 0 | C20: [PENDING_DATA]
A21: Investor net target (CAD/mo) [DRAFT_OP_V5] | B21: 0 | C21: [PENDING_DATA]
A22: Partner_L monthly need (reference) [DRAFT_OP_V5] | B22: 0 | C22: [PENDING_DATA]
A23: Dividend payout ratio (of net profit) [DRAFT_OP_V5] | B23: 0.25 | C23: [PENDING_DATA]
A25: Initial capital — line-item audit (→ INFRASTRUCTURE_ASSETS) [DRAFT_OP_V5] | B25: =INFRASTRUCTURE_ASSETS!$B$9 | C25: [VERIFIED]
A26: Initial capital — valuation rollup (→ CAPEX_SUMMARY) [DRAFT_OP_V5] | B26: =CAPEX_SUMMARY!$B$3 | C26: [VERIFIED]
A28: Legal — incorporation — RANGE (ghost) [DRAFT_OP_V5] | B28: Market Benchmark [QC_2026_DATA]: [$600 – $5,000] QC incorporation (reference band)
A29: Legal — incorporation — ACTUAL (CAD) [DRAFT_OP_V5] | B29: 600 | C29: [VERIFIED]
A30: Marketing (monthly) — RANGE (ghost) [DRAFT_OP_V5] | B30: Market Benchmark [QC_2026_DATA]: [$500 – $2,500] Google Ads (reference band)
A31: Marketing (monthly) — ACTUAL (CAD) [DRAFT_OP_V5] | B31: 500 | C31: [VERIFIED]
A32: Software (Jane App) — RANGE (ghost) [DRAFT_OP_V5] | B32: Market Benchmark [QC_2026_DATA]: [$79 – $109] Jane App (reference band)
A33: Software (Jane App) — ACTUAL (CAD/mo) [DRAFT_OP_V5] | B33: 109 | C33: [VERIFIED]
A34: Initial investment — Marketing launch (one-time) [DRAFT_OP_V5] | B34: 0 | C34: [PENDING_DATA]
A35: Initial investment — Software licenses [DRAFT_OP_V5] | B35: 0 | C35: [PENDING_DATA]
A36: Municipal license / business registration (annual CAD) [DRAFT_OP_V5] | B36: 300 | C36: [PENDING_DATA]
A37: Professional liability — Social Work (annual CAD) [DRAFT_OP_V5] | B37: 400 | C37: [PENDING_DATA]
A38: Professional insurance (QC psych) — RANGE (ghost) [DRAFT_OP_V5] | B38: Market Benchmark [QC_2026_DATA]: [$50 – $100]/mo (reference band)
A39: Professional insurance (QC psych) — ACTUAL (CAD/mo) [DRAFT_OP_V5] | B39: 65 | C39: [VERIFIED]
A40: Monthly — Domain / Hosting / Phone [DRAFT_OP_V5] | B40: 85 | C40: [VERIFIED]
A41: ADJUSTMENT_RESERVE (→ DASHBOARD Input_Variables) [DRAFT_OP_V5] | B41: =DASHBOARD!$N$38 | C41: [VERIFIED]
A42: Initial investment total [DRAFT_OP_V5] | B42: =SUM(B29,B34,B35)
A43: Footnote: [PENDING_DATA] = operational inputs pending user entry. Initial capital (B25–B26) references INFRASTRUCTURE_ASSETS and CAPEX_SUMMARY.

Sheet TIERS
A1: Tier [DRAFT_OP_V5] | B1: Rate_Per_Session (CAD) [DRAFT_OP_V5]
A2: Intern [DRAFT_OP_V5] | B2: 120
A3: Junior [DRAFT_OP_V5] | B3: 150
A4: Senior [DRAFT_OP_V5] | B4: 190

Sheet ROSTER
A1: Therapist_ID [DRAFT_OP_V5] | B1: Tier (Intern / Jr / Sr) [DRAFT_OP_V5] | C1: Weekly_Hours [DRAFT_OP_V5] | D1: Rate_Per_Session (CAD) [DRAFT_OP_V5] | E1: Monthly clinic share [DRAFT_OP_V5] | F1: Monthly gross billing (ref.) [DRAFT_OP_V5]
E2: =$C2*4*$D2*INPUTS!$B$2 | F2: =$C2*4*$D2
E3: =$C3*4*$D3*INPUTS!$B$2 | F3: =$C3*4*$D3
E4: =$C4*4*$D4*INPUTS!$B$2 | F4: =$C4*4*$D4
E5: =$C5*4*$D5*INPUTS!$B$2 | F5: =$C5*4*$D5
E6: =$C6*4*$D6*INPUTS!$B$2 | F6: =$C6*4*$D6
E7: =$C7*4*$D7*INPUTS!$B$2 | F7: =$C7*4*$D7
E8: =$C8*4*$D8*INPUTS!$B$2 | F8: =$C8*4*$D8
E9: =$C9*4*$D9*INPUTS!$B$2 | F9: =$C9*4*$D9
E10: =$C10*4*$D10*INPUTS!$B$2 | F10: =$C10*4*$D10
E11: =$C11*4*$D11*INPUTS!$B$2 | F11: =$C11*4*$D11
E12: =$C12*4*$D12*INPUTS!$B$2 | F12: =$C12*4*$D12
E13: =$C13*4*$D13*INPUTS!$B$2 | F13: =$C13*4*$D13
... E21: =$C21*4*$D21*INPUTS!$B$2 | F21: =$C21*4*$D21
A22: TOTAL [DRAFT_OP_V5] | E22: =SUM(E2:E21) | F22: =SUM(F2:F21)

Sheet OPERATING_COSTS
A1: Operating costs — detail [DRAFT_OP_V5]
A3: Category [DRAFT_OP_V5] | B3: Monthly CAD [DRAFT_OP_V5] | C3: Notes [DRAFT_OP_V5] [PENDING_DATA] | D3: In Path B (light) [DRAFT_OP_V5]
A4: Professional insurance — QC (psych) [DRAFT_OP_V5] | B4: =INPUTS!$B$39 | C4: — | D4: N
A5: Regulatory compliance — OPQ [DRAFT_OP_V5] | B5: 0 | C5: — | D5: N
A6: Software — base stack (excl. Jane) [DRAFT_OP_V5] | B6: 0 | C6: — | D6: Y
A7: Jane App (Compliance) [DRAFT_OP_V5] | B7: =INPUTS!$B$33 | C7: — | D7: Y
A8: Automated marketing (base) [DRAFT_OP_V5] | B8: =INPUTS!$B$31 | C8: — | D8: Y
A9: Domain / Hosting / Phone [DRAFT_OP_V5] | B9: =INPUTS!$B$40 | C9: — | D9: Y
A10: Other operating [DRAFT_OP_V5] | B10: 0 | C10: — | D10: Y
A11: Municipal license / business registration [DRAFT_OP_V5] | B11: =INPUTS!$B$36/12 | C11: — | D11: Y
A12: Professional liability — Social Work [DRAFT_OP_V5] | B12: =INPUTS!$B$37/12 | C12: — | D12: Y
A14: Total monthly (all lines) [DRAFT_OP_V5] | B14: =SUM(B4:B12)
A15: Path B — monthly opex (excl. QC ins. + OPQ) [DRAFT_OP_V5] | B15: =SUMIF(D4:D12,"Y",B4:B12)

Sheet INFRASTRUCTURE_ASSETS
A1: Infrastructure assets — line items (INFRASTRUCTURE_ASSETS.csv) [DRAFT_OP_V5]
A3: Line item [DRAFT_OP_V5] | B3: Hours [DRAFT_OP_V5] | C3: Reference rate ($/hr) [DRAFT_OP_V5] | D3: Value (CAD) [DRAFT_OP_V5]
A4: Gemini Architecture [DRAFT_OP_V5] | B4: 18.5 | C4: 125 | D4: =B4*C4
A5: ChatGPT Mockups [DRAFT_OP_V5] | B5: 8 | C5: 125 | D5: =B5*C5
A6: Grok Research [DRAFT_OP_V5] | B6: 4 | C6: 125 | D6: =B6*C6
A7: Systems Integration (Cursor) [DRAFT_OP_V5] | B7: 2 | C7: 125 | D7: =B7*C7
A8: Software Subscriptions (Cursor/Tools) [DRAFT_OP_V5] | B8: 0 | C8: 0 | D8: 0
A9: Total — line-item value (CAD) [DRAFT_OP_V5] | B9: =SUM(D4:D8)

Sheet CAPEX_SUMMARY
A1: CAPEX_SUMMARY [DRAFT_OP_V5]
A3: Total Initial Valuation (CAD) | B3: =INFRASTRUCTURE_ASSETS!$B$9
A4: Architect's System Contribution | B4: =B3

Sheet PARTNERSHIP_STRUCTURE
A1: Partnership structure — ownership [DRAFT_OP_V5]
A2: Post-money valuation (CAD) [DRAFT_OP_V5] | B2: 0
A4: Party [DRAFT_OP_V5] | B4: Capital ($) [DRAFT_OP_V5] | C4: Sweat hrs [DRAFT_OP_V5] | D4: Rate ($) [DRAFT_OP_V5] | E4: Contribution [DRAFT_OP_V5] | F4: % Own [DRAFT_OP_V5]
A5: Principal A (infrastructure) [DRAFT_OP_V5] | B5: 0 | C5: 0 | D5: 0 | E5: =B5+C5*D5+INFRASTRUCTURE_ASSETS!$B$9 | F5: =IF(SUM($E$5:$E$8)=0,0,E5/SUM($E$5:$E$8))
A6: Partner L [DRAFT_OP_V5] | B6: 0 | C6: 0 | D6: 0 | E6: =B6+C6*D6 | F6: =IF(SUM($E$5:$E$8)=0,0,E6/SUM($E$5:$E$8))
A7: Principal C [DRAFT_OP_V5] | B7: 0 | C7: 0 | D7: 0 | E7: =B7+C7*D7 | F7: =IF(SUM($E$5:$E$8)=0,0,E7/SUM($E$5:$E$8))
A8: Director (res.) [DRAFT_OP_V5] | B8: 0 | C8: 0 | D8: 0 | E8: =B8+C8*D8 | F8: =IF(SUM($E$5:$E$8)=0,0,E8/SUM($E$5:$E$8))
A13: Total [DRAFT_OP_V5] | B13: =SUM(E5:E8)
A14: Δ vs post-money [DRAFT_OP_V5] | B14: =B13-B2

Sheet MODEL
A1: METRIC [DRAFT_OP_V5] | B1: VALUE [DRAFT_OP_V5]
A3: Director — clinic share revenue (solvency anchor) [DRAFT_OP_V5] | B3: =INPUTS!$B$9*INPUTS!$B$10*INPUTS!$B$2
A4: Roster — clinic share [DRAFT_OP_V5] | B4: =ROSTER!$E$22
A5: Total clinic margin [DRAFT_OP_V5] | B5: =B3+B4
A6: Operating_Costs (incl. director hybrid pay) [DRAFT_OP_V5] | B6: =(OPERATING_COSTS!$B$14+IF(COUNTA(ROSTER!$A$2:$A$21)>=INPUTS!$B$12,INPUTS!$B$15,0)+INPUTS!$B$13*INPUTS!$B$14+IF(COUNTA(ROSTER!$A$2:$A$21)<INPUTS!$B$12,0,IF(INPUTS!$B$16>0,ROSTER!$F$22*INPUTS!$B$16,IF(INPUTS!$B$17>0,SUM(ROSTER!$C$2:$C$21)*4*INPUTS!$B$17,0)))+INPUTS!$B$7*INPUTS!$B$8+INPUTS!$B$9*INPUTS!$B$11)
A7: Partner_L_Draw (fixed) [DRAFT_OP_V5] | B7: =INPUTS!$B$6
A8: Pre-tax (before adjustment reserve) [DRAFT_OP_V5] | B8: =B5-B6-B7
A9: Tax [DRAFT_OP_V5] | B9: =IF(B8>0,B8*INPUTS!$B$19,0)
A10: Net after tax (before ADJUSTMENT_RESERVE) [DRAFT_OP_V5] | B10: =B8-B9
A11: ADJUSTMENT_RESERVE (INPUTS — last lever) [DRAFT_OP_V5] | B11: =INPUTS!$B$41
A12: Net profit (final) [DRAFT_OP_V5] | B12: =B10+B11
A13: Alert — equity redemption [DRAFT_OP_V5] | B13: =IF(B12<INPUTS!$B$6,"EQUITY REDEMPTION REQUIRED","")
A14: Validation — solvency (ops + draw > margin) [DRAFT_OP_V5] | B14: =IF(B6+B7>B5,"WARNING: CLINIC INSOLVENT","")
A16: Reference — therapist-side (1 − Clinic %) × gross [DRAFT_OP_V5] | B16: =ROSTER!$F$22*(1-INPUTS!$B$2)
A17: Break-even — roster gross (approx.) [DRAFT_OP_V5] | B17: =IF(ROSTER!$F$22<=0,0,IF(INPUTS!$B$2<=0,0,(OPERATING_COSTS!$B$14+IF(COUNTA(ROSTER!$A$2:$A$21)>=INPUTS!$B$12,INPUTS!$B$15,0)+INPUTS!$B$13*INPUTS!$B$14+IF(COUNTA(ROSTER!$A$2:$A$21)<INPUTS!$B$12,0,IF(INPUTS!$B$16>0,ROSTER!$F$22*INPUTS!$B$16,IF(INPUTS!$B$17>0,SUM(ROSTER!$C$2:$C$21)*4*INPUTS!$B$17,0))))/INPUTS!$B$2))
A18: Dividend pool [DRAFT_OP_V5] | B18: =IF(B12>0,B12*INPUTS!$B$23,0)
A19: Dividend — Principal A [DRAFT_OP_V5] | B19: =$B$18*PARTNERSHIP_STRUCTURE!$F$5
A20: Dividend — Partner L [DRAFT_OP_V5] | B20: =$B$18*PARTNERSHIP_STRUCTURE!$F$6
A21: Dividend — Principal C [DRAFT_OP_V5] | B21: =$B$18*PARTNERSHIP_STRUCTURE!$F$7
A22: Dividend — Director (reserved) [DRAFT_OP_V5] | B22: =$B$18*PARTNERSHIP_STRUCTURE!$F$8
A23: Check (pool) [DRAFT_OP_V5] | B23: =B18-SUM(B19:B22)
A24: Payback (months) [DRAFT_OP_V5] | B24: =IF(AND(B12>0,INPUTS!$B$42>0),INPUTS!$B$42/B12,"—")
A25: Roster hours — investor scale (ref.) [DRAFT_OP_V5] | B25: =IF(OR(B19<=0,INPUTS!$B$21<=0),"—",ROUNDUP(SUM(ROSTER!$C$2:$C$21)*(INPUTS!$B$21/B19),1))

Sheet SCENARIOS
A1: Metric [DRAFT_OP_V5] | B1: 1 | C1: 2 | D1: 3 | E1: 5 | F1: 8
A2: Clinic margin (scaled) [DRAFT_OP_V5] | B2: =IF(COUNTA(ROSTER!$A$2:$A$21)=0,0,MODEL!$B$5*(B$1/MAX(COUNTA(ROSTER!$A$2:$A$21),1))) | C2: =IF(COUNTA(ROSTER!$A$2:$A$21)=0,0,MODEL!$B$5*(C$1/MAX(COUNTA(ROSTER!$A$2:$A$21),1))) | D2: =IF(COUNTA(ROSTER!$A$2:$A$21)=0,0,MODEL!$B$5*(D$1/MAX(COUNTA(ROSTER!$A$2:$A$21),1))) | E2: =IF(COUNTA(ROSTER!$A$2:$A$21)=0,0,MODEL!$B$5*(E$1/MAX(COUNTA(ROSTER!$A$2:$A$21),1))) | F2: =IF(COUNTA(ROSTER!$A$2:$A$21)=0,0,MODEL!$B$5*(F$1/MAX(COUNTA(ROSTER!$A$2:$A$21),1)))
A3: Operating costs (scaled) [DRAFT_OP_V5] | B3: =IF(COUNTA(ROSTER!$A$2:$A$21)=0,0,MODEL!$B$6*(B$1/MAX(COUNTA(ROSTER!$A$2:$A$21),1))) | C3: =IF(COUNTA(ROSTER!$A$2:$A$21)=0,0,MODEL!$B$6*(C$1/MAX(COUNTA(ROSTER!$A$2:$A$21),1))) | D3: =IF(COUNTA(ROSTER!$A$2:$A$21)=0,0,MODEL!$B$6*(D$1/MAX(COUNTA(ROSTER!$A$2:$A$21),1))) | E3: =IF(COUNTA(ROSTER!$A$2:$A$21)=0,0,MODEL!$B$6*(E$1/MAX(COUNTA(ROSTER!$A$2:$A$21),1))) | F3: =IF(COUNTA(ROSTER!$A$2:$A$21)=0,0,MODEL!$B$6*(F$1/MAX(COUNTA(ROSTER!$A$2:$A$21),1)))
A4: Pre-tax after draw [DRAFT_OP_V5] | B4: =B2-B3-INPUTS!$B$6 | C4: =C2-C3-INPUTS!$B$6 | D4: =D2-D3-INPUTS!$B$6 | E4: =E2-E3-INPUTS!$B$6 | F4: =F2-F3-INPUTS!$B$6
A5: Net (tax approx) [DRAFT_OP_V5] | B5: =IF(B4>0,B4*(1-INPUTS!$B$19),B4) | C5: =IF(C4>0,C4*(1-INPUTS!$B$19),C4) | D5: =IF(D4>0,D4*(1-INPUTS!$B$19),D4) | E5: =IF(E4>0,E4*(1-INPUTS!$B$19),E4) | F5: =IF(F4>0,F4*(1-INPUTS!$B$19),F4)
A6: Dividend pool (approx) [DRAFT_OP_V5] | B6: =B5*INPUTS!$B$23 | C6: =C5*INPUTS!$B$23 | D6: =D5*INPUTS!$B$23 | E6: =E5*INPUTS!$B$23 | F6: =F5*INPUTS!$B$23
A8: Clinic % sensitivity — net profit [DRAFT_OP_V5]
A9: Clinic % [DRAFT_OP_V5] | B9: 0.33 | C9: 0.4 | D9: 0.5
A10: Net profit (approx) [DRAFT_OP_V5] | B10: =IF((ROSTER!$F$22*B9+INPUTS!$B$9*INPUTS!$B$10*B9-MODEL!$B$6-INPUTS!$B$6)>0,(ROSTER!$F$22*B9+INPUTS!$B$9*INPUTS!$B$10*B9-MODEL!$B$6-INPUTS!$B$6)*(1-INPUTS!$B$19),(ROSTER!$F$22*B9+INPUTS!$B$9*INPUTS!$B$10*B9-MODEL!$B$6-INPUTS!$B$6)) | C10: =IF((ROSTER!$F$22*C9+INPUTS!$B$9*INPUTS!$B$10*C9-MODEL!$B$6-INPUTS!$B$6)>0,(ROSTER!$F$22*C9+INPUTS!$B$9*INPUTS!$B$10*C9-MODEL!$B$6-INPUTS!$B$6)*(1-INPUTS!$B$19),(ROSTER!$F$22*C9+INPUTS!$B$9*INPUTS!$B$10*C9-MODEL!$B$6-INPUTS!$B$6)) | D10: =IF((ROSTER!$F$22*D9+INPUTS!$B$9*INPUTS!$B$10*D9-MODEL!$B$6-INPUTS!$B$6)>0,(ROSTER!$F$22*D9+INPUTS!$B$9*INPUTS!$B$10*D9-MODEL!$B$6-INPUTS!$B$6)*(1-INPUTS!$B$19),(ROSTER!$F$22*D9+INPUTS!$B$9*INPUTS!$B$10*D9-MODEL!$B$6-INPUTS!$B$6))

Sheet SCENARIO_B_LIGHT
A1: Scenario B — light [DRAFT_OP_V5]
A2: Session price — low [DRAFT_OP_V5] | B2: 120
A3: Session price — high [DRAFT_OP_V5] | B3: 150
A4: Midpoint [DRAFT_OP_V5] | B4: =(B2+B3)/2
A5: Clinic % [DRAFT_OP_V5] | B5: =INPUTS!$B$2
A6: Revenue / session [DRAFT_OP_V5] | B6: =B4*B5
A7: Monthly session-equiv (roster hours × 4) [DRAFT_OP_V5] | B7: =SUM(ROSTER!$C$2:$C$21)*4
A8: Monthly revenue [DRAFT_OP_V5] | B8: =B7*B6
A9: Opex Path B [DRAFT_OP_V5] | B9: =OPERATING_COSTS!$B$15
A10: Supervision (excl.) [DRAFT_OP_V5] | B10: 0
A11: Admin flat [DRAFT_OP_V5] | B11: =IF(COUNTA(ROSTER!$A$2:$A$21)>=INPUTS!$B$12,INPUTS!$B$15,0)
A12: Total costs [DRAFT_OP_V5] | B12: =B9+B10+B11
A14: PBT [DRAFT_OP_V5] | B14: =B8-B12
A15: Tax [DRAFT_OP_V5] | B15: =IF(B14>0,B14*INPUTS!$B$19,0)
A16: Net [DRAFT_OP_V5] | B16: =B14-B15
A18: ROI vs initial [DRAFT_OP_V5] | B18: =IF(INPUTS!$B$42<=0,"—",(B16*12)/INPUTS!$B$42)

Sheet PARTNER_L_COVERAGE
A1: Partner_L — fixed draw vs modeled economics [DRAFT_OP_V5]
A3: Partner_L_Draw (target) [DRAFT_OP_V5] | B3: =INPUTS!$B$6
A4: Net profit (MODEL) [DRAFT_OP_V5] | B4: =MODEL!$B$12
A5: Partner_L dividend (PARTNERSHIP_STRUCTURE) [DRAFT_OP_V5] | B5: =MODEL!$B$20
A6: Gap (draw − dividend) [DRAFT_OP_V5] | B6: =MAX(0,B3-B5)

Sheet DASHBOARD
A2: Total clinic margin [DRAFT_OP_V5] | B2: =MODEL!B5
A3: Net profit (final) [DRAFT_OP_V5] | B3: =MODEL!B12
A4: Break-even gross (roster ref.) [DRAFT_OP_V5] | B4: =MODEL!B17
A5: Payback [DRAFT_OP_V5] | B5: =MODEL!B24
A6: Dividend pool [DRAFT_OP_V5] | B6: =MODEL!B18
A7: Investor scale (hours) [DRAFT_OP_V5] | B7: =MODEL!B25
A8: Path B net [DRAFT_OP_V5] | B8: =SCENARIO_B_LIGHT!B16
A9: Partner_L coverage gap [DRAFT_OP_V5] | B9: =PARTNER_L_COVERAGE!B6
A10: Solvency [DRAFT_OP_V5] | B10: =MODEL!B14
A11: Initial capital — valuation (INITIAL_CAPITAL_VALUATION.csv) [DRAFT_OP_V5] | B11: =INPUTS!$B$26
A12: ROI — initial capital (valuation) [DRAFT_OP_V5] | B12: =IF(INPUTS!$B$26<=0,"—",(MODEL!$B$12*12)/INPUTS!$B$26)
A13: Redemption alert [DRAFT_OP_V5] | B13: =MODEL!B13
A24: Clinical Operations System — Master Dossier (Print View) [DRAFT_OP_V5]
A25: Total clinic margin (CAD/mo) | B25: =MODEL!B5
A26: Net profit — final (CAD/mo) | B26: =MODEL!B12
A27: Partner_L_Draw (CAD/mo) | B27: =INPUTS!B6
A28: Redemption flag (MODEL) | B28: =MODEL!B13
A29: Initial capital — line-item audit (INPUTS) | B29: =INPUTS!B25
M37: Input_Variables
M38: ADJUSTMENT_RESERVE | N38: 0

Sheet EXPENSES
A1: Category [DRAFT_OP_V5] | B1: Monthly [DRAFT_OP_V5] | C1: Annual [DRAFT_OP_V5] | D1: Include? [DRAFT_OP_V5]
A2: Director hybrid pay [DRAFT_OP_V5] | B2: =INPUTS!$B$7*INPUTS!$B$8+INPUTS!$B$9*INPUTS!$B$11 | C2: =B2*12 | D2: TRUE
A3: Other variable (legacy + admin + supervision) [DRAFT_OP_V5] | B3: =MODEL!$B$6-OPERATING_COSTS!$B$14-B2 | C3: =B3*12 | D3: TRUE
A4: =OPERATING_COSTS!$A$4 | B4: =OPERATING_COSTS!$B$4 | C4: =B4*12 | D4: TRUE
A5: =OPERATING_COSTS!$A$5 | B5: =OPERATING_COSTS!$B$5 | C5: =B5*12 | D5: TRUE
A6: =OPERATING_COSTS!$A$6 | B6: =OPERATING_COSTS!$B$6 | C6: =B6*12 | D6: TRUE
A7: =OPERATING_COSTS!$A$7 | B7: =OPERATING_COSTS!$B$7 | C7: =B7*12 | D7: TRUE
A8: =OPERATING_COSTS!$A$8 | B8: =OPERATING_COSTS!$B$8 | C8: =B8*12 | D8: TRUE
A9: =OPERATING_COSTS!$A$9 | B9: =OPERATING_COSTS!$B$9 | C9: =B9*12 | D9: TRUE
A10: =OPERATING_COSTS!$A$10 | B10: =OPERATING_COSTS!$B$10 | C10: =B10*12 | D10: TRUE
A11: =OPERATING_COSTS!$A$11 | B11: =OPERATING_COSTS!$B$11 | C11: =B11*12 | D11: TRUE
A12: =OPERATING_COSTS!$A$12 | B12: =OPERATING_COSTS!$B$12 | C12: =B12*12 | D12: TRUE
A13: Law 25 privacy [PENDING_DATA] [DRAFT_OP_V5] | B13: 0 | C13: =B13*12 | D13: TRUE
A14: Total monthly [DRAFT_OP_V5] | B14: =SUMIF(D2:D13,TRUE,B2:B13)

Sheet PRINT_SUMMARY
A1: [PROJECT_ID: COS-2026-QC]
A4: Clinical Operations System (COS) — financial reporting extract
A5: Executive summary — CAPEX, OpEx, solvency (linked)
A6: CAPEX — Total Initial Valuation (CAPEX_SUMMARY) | B6: =CAPEX_SUMMARY!B3
A7: Monthly OpEx — operating detail (OPERATING_COSTS) | B7: =OPERATING_COSTS!$B$14
A8: Total operating load incl. hybrid pay (MODEL) | B8: =MODEL!B6
A9: Net profit — final (MODEL) | B9: =MODEL!B12
A10: Solvency validation (MODEL) | B10: =MODEL!B14
A11: Redemption alert text (MODEL) | B11: =MODEL!B13
